Workbook
Name avg_equity: Ratios!$C$27
Name avg_total_assets: Ratios!$C$28
Name avg_total_capitalization: Ratios!$C$29
Name book_equity: Ratios!$C$18
Name cash: Ratios!$C$19
Name cogs: Ratios!$C$38
Name cost_of_capital: Ratios!$C$7
Name current_assets_total: Ratios!$C$20
Name current_liabilities_total: Ratios!$C$21
Name currentYear_after_tax_operating_income: Ratios!$C$16
Name currentYear_assets_total: Ratios!$C$24
Name currentYear_total_capitalization: Ratios!$C$25
Name daily_sales: Ratios!$C$17
Name depreciation_amortization: Ratios!$C$39
Name ebit: Ratios!$C$32
Name interest_total: Ratios!$C$33
Name inventory_current: Ratios!$C$36
Name long_term_debt: Ratios!$C$22
Name long_term_debt_plus_equity: Ratios!$C$30
Name market_capitalization: Ratios!$C$9
Name net_income: Ratios!$C$35
Name nwc: Ratios!$C$23
Name pretax_profit: Ratios!$C$34
Name receivables_current: Ratios!$C$37
Name revenue: Ratios!$C$31
Name share_price: Ratios!$C$5
Name shares_outstanding: Ratios!$C$6
Name startYear_assets_total: Ratios!$C$13
Name startYear_equity: Ratios!$C$10
Name startYear_inventories: Ratios!$C$11
Name startYear_lt_debt: Ratios!$C$14
Name startYear_receivables: Ratios!$C$12
Name startYear_total_capitalization: Ratios!$C$15
Name tax_rate: Ratios!$C$8
Name total_liabilities: Ratios!$C$26

Sheet Balance Sheet
A1: Caterpillar Inc. – Balance Sheet (FY2025 / FY2024)
A3: Line Item | B3: FY2025 ($mm) | C3: FY2024 ($mm) | D3: Notes
A4: Cash and cash equivalents | B4: 9980 | C4: 6889 | D4: Values mapped from Caterpillar 2025 Form 10-K Excel data.
A5: Receivables - trade and other | B5: 10920 | C5: 9282 | D5: Values mapped from Caterpillar 2025 Form 10-K Excel data.
A6: Receivables - finance | B6: 10649 | C6: 9565 | D6: Values mapped from Caterpillar 2025 Form 10-K Excel data.
A7: Prepaid expenses and other current assets | B7: 2801 | C7: 3119 | D7: Values mapped from Caterpillar 2025 Form 10-K Excel data.
A8: Inventories | B8: 18135 | C8: 16827 | D8: Values mapped from Caterpillar 2025 Form 10-K Excel data.
A9: Total current assets | B9: 52485 | C9: 45682 | D9: Values mapped from Caterpillar 2025 Form 10-K Excel data.
A10: Property, plant and equipment - net | B10: 15140 | C10: 13361 | D10: Values mapped from Caterpillar 2025 Form 10-K Excel data.
A11: Long-term receivables - trade and other | B11: 2142 | C11: 1225 | D11: Values mapped from Caterpillar 2025 Form 10-K Excel data.
A12: Long-term receivables - finance | B12: 14272 | C12: 13242 | D12: Values mapped from Caterpillar 2025 Form 10-K Excel data.
A13: Noncurrent deferred and refundable income taxes | B13: 2882 | C13: 3312 | D13: Values mapped from Caterpillar 2025 Form 10-K Excel data.
A14: Intangible assets | B14: 241 | C14: 399 | D14: Values mapped from Caterpillar 2025 Form 10-K Excel data.
A15: Goodwill | B15: 5321 | C15: 5241 | D15: Values mapped from Caterpillar 2025 Form 10-K Excel data.
... A39: Total liabilities and shareholders' equity | B39: 98585 | C39: 87764 | D39: Values mapped from Caterpillar 2025 Form 10-K Excel data.

Sheet Income Statement
A1: Caterpillar Inc. – Income Statement (FY2025 / FY2024)
A3: Line Item | B3: FY2025 ($mm) | C3: FY2024 ($mm) | D3: Notes
A4: Sales of Machinery, Power & Energy | B4: 63980 | C4: 61363 | D4: Values mapped from Caterpillar 2025 Form 10-K Excel data.
A5: Revenues of Financial Products | B5: 3609 | C5: 3446 | D5: Values mapped from Caterpillar 2025 Form 10-K Excel data.
A6: Total sales and revenues | B6: 67589 | C6: 64809 | D6: Values mapped from Caterpillar 2025 Form 10-K Excel data.
A7: Cost of goods sold | B7: 44752 | C7: 40199 | D7: Values mapped from Caterpillar 2025 Form 10-K Excel data.
A8: Selling, general and administrative expenses | B8: 6985 | C8: 6667 | D8: Values mapped from Caterpillar 2025 Form 10-K Excel data.
A9: Research and development expenses | B9: 2148 | C9: 2107 | D9: Values mapped from Caterpillar 2025 Form 10-K Excel data.
A10: Interest expense of Financial Products | B10: 1359 | C10: 1286 | D10: Values mapped from Caterpillar 2025 Form 10-K Excel data.
A11: Other operating (income) expenses | B11: 1194 | C11: 1478 | D11: Values mapped from Caterpillar 2025 Form 10-K Excel data.
A12: Total operating costs | B12: 56438 | C12: 51737 | D12: Values mapped from Caterpillar 2025 Form 10-K Excel data.
A13: Operating profit (EBIT) | B13: 11151 | C13: 13072 | D13: Values mapped from Caterpillar 2025 Form 10-K Excel data.
A14: Interest expense excluding Financial Products | B14: 502 | C14: 512 | D14: Values mapped from Caterpillar 2025 Form 10-K Excel data.
A15: Other income (expense) | B15: 892 | C15: 813 | D15: Values mapped from Caterpillar 2025 Form 10-K Excel data.
... A23: Diluted EPS | B23: 18.81 | C23: 22.05 | D23: Values mapped from Caterpillar 2025 Form 10-K Excel data.

Sheet Cash Flow
A1: Caterpillar Inc. – Cash Flow Statement (FY2025 / FY2024)
A3: Line Item | B3: FY2025 ($mm) | C3: FY2024 ($mm) | D3: Notes
A4: Profit of consolidated and affiliated companies | B4: 8882 | C4: 10788 | D4: Values mapped from Caterpillar 2025 Form 10-K Excel data.
A5: Depreciation and amortization | B5: 2262 | C5: 2153 | D5: Values mapped from Caterpillar 2025 Form 10-K Excel data.
A6: Provision (benefit) for deferred income taxes | B6: 465 | C6: -621 | D6: Values mapped from Caterpillar 2025 Form 10-K Excel data.
A7: (Gain) loss on divestiture | B7: 30 | C7: 164 | D7: Values mapped from Caterpillar 2025 Form 10-K Excel data.
A8: Receivables - trade and other | B8: -2138 | C8: -160 | D8: Values mapped from Caterpillar 2025 Form 10-K Excel data.
A9: Inventories | B9: -1477 | C9: -414 | D9: Values mapped from Caterpillar 2025 Form 10-K Excel data.
A10: Accounts payable | B10: 1179 | C10: -282 | D10: Values mapped from Caterpillar 2025 Form 10-K Excel data.
A11: Accrued expenses | B11: 438 | C11: 191 | D11: Values mapped from Caterpillar 2025 Form 10-K Excel data.
A12: Accrued wages, salaries and employee benefits | B12: 187 | C12: -363 | D12: Values mapped from Caterpillar 2025 Form 10-K Excel data.
A13: Customer advances | B13: 1933 | C13: 370 | D13: Values mapped from Caterpillar 2025 Form 10-K Excel data.
A14: Other assets - net | B14: -176 | C14: -97 | D14: Values mapped from Caterpillar 2025 Form 10-K Excel data.
A15: Other liabilities - net | B15: -294 | C15: -104 | D15: Values mapped from Caterpillar 2025 Form 10-K Excel data.
... A26: Cash, cash equivalents and restricted cash at end of period | B26: 9986 | C26: 6896 | D26: Values mapped from Caterpillar 2025 Form 10-K Excel data.

Sheet Ratios
A1: Caterpillar Inc. – Ratio Model (latest available data)
A3: Named Range / Key | B3: Description | C3: Value | D3: Units | E3: Source / Formula Note
A5: share_price | B5: Share price (entered from IR trade history) | C5: 716.33 | D5: USD/share | E5: Assumption / market input; update as needed
A6: shares_outstanding | B6: Shares outstanding at Dec. 31 | C6: ='Income Statement'!B22 -> 465.3 | D6: mm shares | E6: Linked from Income Statement
A7: cost_of_capital | B7: Cost of capital (WACC) | C7: 0.1 | D7: % | E7: Editable assumption
A8: tax_rate | B8: Effective tax rate | C8: ='Income Statement'!B17/'Income Statement'!B16 -> 0.23984057 | D8: % | E8: Provision for taxes / pretax profit
A9: market_capitalization | B9: Market capitalization | C9: =C5*C6 -> 333308.35 | D9: $mm | E9: Share price × shares outstanding
A10: startYear_equity | B10: Beginning equity (FY2024) | C10: ='Balance Sheet'!C38 -> 19494 | D10: $mm | E10: Prior-year balance sheet
A11: startYear_inventories | B11: Beginning inventories (FY2024) | C11: ='Balance Sheet'!C8 -> 16827 | D11: $mm | E11: Prior-year balance sheet
A12: startYear_receivables | B12: Beginning receivables - trade and other (FY2024) | C12: ='Balance Sheet'!C5 -> 9282 | D12: $mm | E12: Prior-year balance sheet
A13: startYear_assets_total | B13: Beginning total assets (FY2024) | C13: ='Balance Sheet'!C17 -> 87764 | D13: $mm | E13: Prior-year balance sheet
A14: startYear_lt_debt | B14: Beginning long-term debt (FY2024) | C14: ='Balance Sheet'!C28+'Balance Sheet'!C29 -> 27351 | D14: $mm | E14: LT debt due after one year
A15: startYear_total_capitalization | B15: Beginning total capitalization (LT debt + equity) | C15: =C14+C10 -> 46845 | D15: $mm | E15: Beginning LT debt + beginning equity
A16: currentYear_after_tax_operating_income | B16: Current-year after-tax operating income (NOPAT) | C16: ='Income Statement'!B13*(1-C8) -> 8476.5378 | D16: $mm | E16: EBIT × (1-tax rate)
A17: daily_sales | B17: Current-year daily sales | C17: ='Income Statement'!B6/365 -> 185.17534 | D17: $mm/day | E17: Revenue ÷ 365
A18: book_equity | B18: Current-year book equity | C18: ='Balance Sheet'!B38 -> 21318 | D18: $mm | E18: Current-year total shareholders' equity
A19: cash | B19: Current-year cash | C19: ='Balance Sheet'!B4 -> 9980 | D19: $mm | E19: Current-year cash and cash equivalents
A20: current_assets_total | B20: Current-year current assets | C20: ='Balance Sheet'!B9 -> 52485 | D20: $mm | E20: Current-year total current assets
A21: current_liabilities_total | B21: Current-year current liabilities | C21: ='Balance Sheet'!B27 -> 36558 | D21: $mm | E21: Current-year total current liabilities
A22: long_term_debt | B22: Current-year long-term debt (due after one year) | C22: ='Balance Sheet'!B28+'Balance Sheet'!B29 -> 30696 | D22: $mm | E22: Current-year LT debt due after one year
A23: nwc | B23: Net working capital | C23: =C20-C21 -> 15927 | D23: $mm | E23: Current assets - current liabilities
A24: currentYear_assets_total | B24: Current-year total assets | C24: ='Balance Sheet'!B17 -> 98585 | D24: $mm | E24: Current-year total assets
A25: currentYear_total_capitalization | B25: Current-year total capitalization | C25: =C22+C18 -> 52014 | D25: $mm | E25: Current LT debt + current equity
A26: total_liabilities | B26: Current-year total liabilities | C26: ='Balance Sheet'!B32 -> 77267 | D26: $mm | E26: Current-year total liabilities
A27: avg_equity | B27: Average equity | C27: =(C10+C18)/2 -> 20406 | D27: $mm | E27: Average of beginning and ending equity
A28: avg_total_assets | B28: Average total assets | C28: =(C13+C24)/2 -> 93174.5 | D28: $mm | E28: Average of beginning and ending total assets
A29: avg_total_capitalization | B29: Average total capitalization | C29: =(C15+C25)/2 -> 49429.5 | D29: $mm | E29: Average of beginning and ending capitalization
A30: long_term_debt_plus_equity | B30: Long-term debt + equity | C30: =C22+C18 -> 52014 | D30: $mm | E30: Same as current-year total capitalization
A31: revenue | B31: Current-year sales and revenues | C31: ='Income Statement'!B6 -> 67589 | D31: $mm | E31: Current-year total sales and revenues
A32: ebit | B32: Current-year EBIT | C32: ='Income Statement'!B13 -> 11151 | D32: $mm | E32: Current-year operating profit
A33: interest_total | B33: Total interest expense | C33: ='Income Statement'!B10+'Income Statement'!B14 -> 1861 | D33: $mm | E33: Financial Products interest + ex-FP interest
A34: pretax_profit | B34: Pretax profit | C34: ='Income Statement'!B16 -> 11541 | D34: $mm | E34: Consolidated profit before taxes
A35: net_income | B35: Profit attributable to common shareholders | C35: ='Income Statement'!B19 -> 8884 | D35: $mm | E35: Net income used for ROE and EPS
A36: inventory_current | B36: Current-year inventory | C36: ='Balance Sheet'!B8 -> 18135 | D36: $mm | E36: Current-year inventories
A37: receivables_current | B37: Current-year receivables - trade and other | C37: ='Balance Sheet'!B5 -> 10920 | D37: $mm | E37: Current-year receivables - trade and other
A38: cogs | B38: Cost of goods sold | C38: ='Income Statement'!B7 -> 44752 | D38: $mm | E38: Current-year cost of goods sold
A39: depreciation_amortization | B39: Depreciation and amortization | C39: ='Cash Flow'!B5 -> 2262 | D39: $mm | E39: Current-year D&A from cash flow statement
A41: Ratio Calculations
A42: Category | B42: Ratio | C42: Computed Value | D42: Formula in named-range notation | E42: Comment
A43: Performance | B43: Market Value Added (MVA) | C43: =C9-C18 -> 311990.35 | D43: market_capitalization - book_equity | E43: Equity market value less book equity
A44: Performance | B44: Market-to-Book | C44: =C9/C18 -> 15.635067 | D44: market_capitalization / book_equity | E44: Equity multiple
A45: Performance | B45: Economic Value Added (EVA) | C45: =C16-(C29*C7) -> 3533.5878 | D45: currentYear_after_tax_operating_income - (avg_total_capitalization * cost_of_capital) | E45: NOPAT less capital charge
A46: Profitability | B46: ROA (start-of-year) | C46: =C35/C13 -> 0.10122602 | D46: net_income / startYear_assets_total | E46: Net income over beginning total assets
A47: Profitability | B47: ROC (start-of-year) | C47: =C16/C15 -> 0.18094861 | D47: currentYear_after_tax_operating_income / startYear_total_capitalization | E47: NOPAT over beginning capitalization
A48: Profitability | B48: ROE (start-of-year) | C48: =C35/C10 -> 0.45572997 | D48: net_income / startYear_equity | E48: Net income over beginning equity
A49: Profitability | B49: ROA (average) | C49: =C35/C28 -> 0.095347976 | D49: net_income / avg_total_assets | E49: Net income over average assets
A50: Profitability | B50: ROC (average) | C50: =C16/C29 -> 0.17148743 | D50: currentYear_after_tax_operating_income / avg_total_capitalization | E50: NOPAT over average capitalization
A51: Profitability | B51: ROE (average) | C51: =C35/C27 -> 0.43536215 | D51: net_income / avg_equity | E51: Net income over average equity
A52: Efficiency | B52: Asset Turnover | C52: =C31/C28 -> 0.72540234 | D52: revenue / avg_total_assets | E52: Revenue per average asset dollar
A53: Efficiency | B53: Receivables Turnover | C53: =C31/((C12+C37)/2) -> 6.6913177 | D53: revenue / avg_receivables | E53: Uses average trade & other receivables
A54: Efficiency | B54: Avg Collection Period | C54: =365/(C31/((C12+C37)/2)) -> 54.548299 | D54: 365 / receivables_turnover | E54: Days sales outstanding
A55: Efficiency | B55: Inventory Turnover | C55: =C38/((C11+C36)/2) -> 2.5600366 | D55: cogs / avg_inventory | E55: Uses average inventories
A56: Efficiency | B56: Days in Inventory | C56: =365/(C38/((C11+C36)/2)) -> 142.57609 | D56: 365 / inventory_turnover | E56: Inventory days on hand
A57: Efficiency | B57: Profit Margin | C57: =C35/C31 -> 0.13144151 | D57: net_income / revenue | E57: Net profit margin
A58: Efficiency | B58: Operating Profit Margin | C58: =C32/C31 -> 0.16498247 | D58: ebit / revenue | E58: Operating margin
A59: Leverage | B59: Long-term Debt Ratio | C59: =C22/C25 -> 0.59014881 | D59: long_term_debt / currentYear_total_capitalization | E59: LT debt as a share of capitalization
A60: Leverage | B60: Debt-Equity Ratio | C60: =C22/C18 -> 1.4399099 | D60: long_term_debt / book_equity | E60: Long-term debt to equity
A61: Leverage | B61: Total Debt Ratio | C61: =C26/C24 -> 0.78376021 | D61: total_liabilities / currentYear_assets_total | E61: Total liabilities as share of assets
A62: Leverage | B62: Times Interest Earned | C62: =C32/C33 -> 5.9919398 | D62: ebit / interest_total | E62: EBIT / total interest expense
A63: Leverage | B63: Cash Coverage | C63: =(C32+C39)/C33 -> 7.2074154 | D63: (ebit + depreciation_amortization) / interest_total | E63: EBITDA-style interest coverage
A64: Leverage | B64: Debt Burden | C64: =C34/C32 -> 1.0349744 | D64: pretax_profit / ebit | E64: Can exceed 1.0x when other income is positive
A65: Leverage | B65: Leverage Ratio | C65: =C28/C27 -> 4.5660345 | D65: avg_total_assets / avg_equity | E65: Financial leverage in DuPont
A66: Liquidity | B66: NWC-to-Assets | C66: =C23/C24 -> 0.16155602 | D66: nwc / currentYear_assets_total | E66: Working capital intensity
A67: Liquidity | B67: Current Ratio | C67: =C20/C21 -> 1.4356639 | D67: current_assets_total / current_liabilities_total | E67: Current assets / current liabilities
A68: Liquidity | B68: Quick Ratio | C68: =(C20-C36)/C21 -> 0.93960282 | D68: (current_assets_total - inventory_current) / current_liabilities_total | E68: Excludes inventory
A69: Liquidity | B69: Cash Ratio | C69: =C19/C21 -> 0.27299086 | D69: cash / current_liabilities_total | E69: Cash only
A70: Du Pont | B70: ROA decomposition | C70: =(C35/C31)*(C31/C28) -> 0.095347976 | D70: (net_income / revenue) * (revenue / avg_total_assets) | E70: Should tie to ROA (average)
A71: Du Pont | B71: ROE decomposition | C71: =(C35/C34)*(C34/C32)*(C32/C31)*(C31/C28)*(C28/C27) -> 0.43536215 | D71: (net_income / pretax_profit) * (pretax_profit / ebit) * (ebit / revenue) * (revenue / avg_total_assets) * (avg_total_assets / avg_equity) | E71: Five-step DuPont ROE
A73: Model Checks
A74: Check | B74: Formula | C74: Result | D74: Target | E74: Status
A75: DuPont ROA tie | B75: '=ABS(C70-C49) | C75: =ABS(C70-C49) -> 0 | D75: < 0.0001 | E75: =IF(C75<0.0001,"PASS",IF(C75<0.02,"PASS","REVIEW")) -> PASS
A76: DuPont ROE tie | B76: '=ABS(C71-C51) | C76: =ABS(C71-C51) -> 5.5511151e-17 | D76: < 0.0001 | E76: =IF(C76<0.0001,"PASS",IF(C76<0.02,"PASS","REVIEW")) -> PASS
A77: NWC sign vs Current Ratio | B77: '=IF(AND(C67>1,C23>0),1,IF(AND(C67<1,C23<0),1,0)) | C77: =IF(AND(C67>1,C23>0),1,IF(AND(C67<1,C23<0),1,0)) -> 1 | D77: 1 = pass | E77: =IF(C77=1,"PASS","REVIEW") -> PASS
A78: Yahoo market-cap reasonableness | B78: '=ABS(C9-333710)/333710 | C78: =ABS(C9-333710)/333710 -> 0.0012035929 | D78: < 0.02 | E78: =IF(C78<0.0001,"PASS",IF(C78<0.02,"PASS","REVIEW")) -> PASS
A80: Outputs Summary
A81: Category | B81: Ratio | C81: Output Value | D81: Named-range notation | E81: Audit Ref
A82: =A43 -> Performance | B82: =B43 -> Market Value Added (MVA) | C82: =C43 -> 311990.35 | D82: =D43 -> market_capitalization - book_equity | E82: =ROW(C43) -> 43
A83: =A44 -> Performance | B83: =B44 -> Market-to-Book | C83: =C44 -> 15.635067 | D83: =D44 -> market_capitalization / book_equity | E83: =ROW(C44) -> 44
A84: =A45 -> Performance | B84: =B45 -> Economic Value Added (EVA) | C84: =C45 -> 3533.5878 | D84: =D45 -> currentYear_after_tax_operating_income - (avg_total_capitalization * cost_of_capital) | E84: =ROW(C45) -> 45
A85: =A46 -> Profitability | B85: =B46 -> ROA (start-of-year) | C85: =C46 -> 0.10122602 | D85: =D46 -> net_income / startYear_assets_total | E85: =ROW(C46) -> 46
A86: =A47 -> Profitability | B86: =B47 -> ROC (start-of-year) | C86: =C47 -> 0.18094861 | D86: =D47 -> currentYear_after_tax_operating_income / startYear_total_capitalization | E86: =ROW(C47) -> 47
A87: =A48 -> Profitability | B87: =B48 -> ROE (start-of-year) | C87: =C48 -> 0.45572997 | D87: =D48 -> net_income / startYear_equity | E87: =ROW(C48) -> 48
A88: =A49 -> Profitability | B88: =B49 -> ROA (average) | C88: =C49 -> 0.095347976 | D88: =D49 -> net_income / avg_total_assets | E88: =ROW(C49) -> 49
A89: =A50 -> Profitability | B89: =B50 -> ROC (average) | C89: =C50 -> 0.17148743 | D89: =D50 -> currentYear_after_tax_operating_income / avg_total_capitalization | E89: =ROW(C50) -> 50
A90: =A51 -> Profitability | B90: =B51 -> ROE (average) | C90: =C51 -> 0.43536215 | D90: =D51 -> net_income / avg_equity | E90: =ROW(C51) -> 51
A91: =A52 -> Efficiency | B91: =B52 -> Asset Turnover | C91: =C52 -> 0.72540234 | D91: =D52 -> revenue / avg_total_assets | E91: =ROW(C52) -> 52
A92: =A53 -> Efficiency | B92: =B53 -> Receivables Turnover | C92: =C53 -> 6.6913177 | D92: =D53 -> revenue / avg_receivables | E92: =ROW(C53) -> 53
A93: =A54 -> Efficiency | B93: =B54 -> Avg Collection Period | C93: =C54 -> 54.548299 | D93: =D54 -> 365 / receivables_turnover | E93: =ROW(C54) -> 54
... A110: =A71 -> Du Pont | B110: =B71 -> ROE decomposition | C110: =C71 -> 0.43536215 | D110: =D71 -> (net_income / pretax_profit) * (pretax_profit / ebit) * (ebit / revenue) * (revenue / avg_total_assets) * (avg_total_assets / avg_equity) | E110: =ROW(C71) -> 71

Sheet Notes
A1: Notes / Sources / Assumptions
A3: Type | B3: Detail | C3: URL | D3: Status
A4: Primary SEC source | B4: Latest Caterpillar 10-K filing detail page. Current fiscal year in model = FY2025; prior year = FY2024. | C4: https://www.sec.gov/Archives/edgar/data/18230/000001823026000008/0000018230-26-000008-index.htm | D4: Used
A5: Investor Relations filing source | B5: Caterpillar IR filing details page for the FY2025 Form 10-K, including downloadable Excel data. | C5: https://investors.caterpillar.com/financials/sec-filings/sec-filings-details/default.aspx?FilingId=19144813 | D5: Used
A6: Investor results source | B6: 4Q and full-year 2025 results page used as a cross-check for FY2025 revenue, operating margin, enterprise operating cash flow and enterprise cash. | C6: https://investors.caterpillar.com/news/news-details/2026/Caterpillar-Reports-Fourth-Quarter-and-Full-Year-2025-Results/default.aspx | D6: Used
A7: Investor market source | B7: Share price input uses Caterpillar IR stock trade history. Entered model price = 716.33, trade date April 7, 2026. | C7: https://investors.caterpillar.com/stock-info/stock-trade-history/default.aspx | D7: Used
A8: Yahoo Finance source | B8: Yahoo quote page used as a market-cap cross-check (snippet showed market cap of about $333.71B at time of access). | C8: https://finance.yahoo.com/quote/CAT/ | D8: Used
A9: Assumption | B9: Cost of capital (WACC) is a model assumption and remains editable. | D9: Review
A10: Assumption | B10: Ratios are calculated from direct worksheet cell references so they display correctly even if spreadsheet apps mishandle named ranges. | D10: Used
A11: Method note | B11: Named ranges are still defined on the Ratios input cells for auditability and to match the course convention. | D11: Used
A12: Check | B12: DuPont ROA should exactly match average ROA, and DuPont ROE should exactly match average ROE within rounding. | D12: Pass
A13: Check | B13: Market capitalization is calculated as share price × shares outstanding; compare to Yahoo market cap as a reasonableness check. | D13: Pass
